{
  "14.a" : [
    6896
  ],
  "13.a" : [
    6895
  ],
  "4|?1" : [
    6875
  ],
  "11.a" : [
    6889
  ],
  "17|then" : [
    6904
  ],
  "17.b.ii|then" : [
    6915
  ],
  "17.b" : [
    6911
  ],
  "18.a" : [
    6921
  ],
  "17.a" : [
    6909
  ],
  "12|if" : [
    6891
  ],
  "16|then" : [
    6900
  ],
  "17.b.ii" : [
    6914
  ],
  "16|if" : [
    6899
  ],
  "5|if" : [
    6879
  ],
  "17.b.iv" : [
    6918
  ],
  "11" : [
    6888
  ],
  "17|else" : [
    6903
  ],
  "12" : [
    6891
  ],
  "13" : [
    6894
  ],
  "3|?1" : [
    6869
  ],
  "15" : [
    6897
  ],
  "1.a" : [
    6863
  ],
  "16" : [
    6899
  ],
  "17" : [
    6902
  ],
  "18" : [
    6920
  ],
  "19" : [
    6923
  ],
  "17.b.i" : [
    6912
  ],
  "1" : [
    6862
  ],
  "3" : [
    6866
  ],
  "4" : [
    6872
  ],
  "5" : [
    6878
  ],
  "12|then" : [
    6892
  ],
  "17.b.ii|if" : [
    6914
  ],
  "6" : [
    6883
  ],
  "7" : [
    6884
  ],
  "8" : [
    6886,
    6887
  ],
  "17|if" : [
    6903,
    6908
  ],
  "5|then" : [
    6880
  ],
  "17.b.iii" : [
    6916
  ]
}