{
  "11" : [
    22147
  ],
  "5|?1" : [
    22131
  ],
  "4|?1" : [
    22124
  ],
  "2|?1" : [
    22118
  ],
  "7|then" : [
    22138
  ],
  "6|then" : [
    22135
  ],
  "1" : [
    22114
  ],
  "2" : [
    22115
  ],
  "3" : [
    22120
  ],
  "4" : [
    22121
  ],
  "5" : [
    22127
  ],
  "6" : [
    22134
  ],
  "7" : [
    22137
  ],
  "8" : [
    22140
  ],
  "7|if" : [
    22137
  ],
  "9" : [
    22145
  ],
  "6|if" : [
    22134
  ],
  "5|if" : [
    22127
  ],
  "5|then" : [
    22128
  ]
}