{
  "2789" : {
    "2789|3" : "@A.7.C.1.A.751.g.1.A.256.B.1./.1.4.1.A.496.=.1."
  },
  "2788" : {
    "2788|3" : "@A.9.f.1.A.2737.g.1.A.737.P.1./.1.g.1.A.12.g.1.A.755."
  },
  "2825" : {
    "2825|3" : "@A.7.B.1.g.1.A.750.Q.1.A.259.i.1.A.1.E.1.A.493.=.1."
  },
  "2082" : {
    "2082|3" : "@A.1.Q.1.A.20.0.1.A.131.B.1.A.8.q.1.3.1.2.1.A.377.P.1.A.5.Q.1.A.702.8.1.A.35.I.1.A.9.g.2.A.274./.2.w.1.A.184.B.1.A.4.V.1.S.2.A.1016.B.1.A.28.C.1.A.20.w.1.A.282.E.1.A.161.E.1.A.1.B.1.A.15.B.1.A.129.G.1.A.471.C.1.A.132.E.1.A.1.H.1.f.1.y.1.Q.1.A.18.B.1.3.1.8.1.Q.1.A.1.B.1.g.1.A.1.B.1./.1.+.1.g.1.E.1.+.1.8.1.P.1.3.1.9.1./.2.+.1.s.1.A.3.H.1./.1.A.706.=.2."
  }
}