{
  "15.a" : [
    15414
  ],
  "8.f.i" : [
    15386
  ],
  "25.f.i|if" : [
    15463
  ],
  "6.a.i|then" : [
    15365
  ],
  "30.a" : [
    15477
  ],
  "25.e.ii" : [
    15447
  ],
  "15.d" : [
    15417
  ],
  "15.c" : [
    15416
  ],
  "6.a.ii.1" : [
    15368
  ],
  "8.h.ii" : [
    15398
  ],
  "25.e.iii" : [
    15450
  ],
  "10" : [
    15405
  ],
  "11" : [
    15407
  ],
  "25.c.i" : [
    15440
  ],
  "12" : [
    15409
  ],
  "14" : [
    15410
  ],
  "25.g.i" : [
    15467
  ],
  "16" : [
    15418
  ],
  "8.h.iii" : [
    15402
  ],
  "17" : [
    15419
  ],
  "18" : [
    15421
  ],
  "19" : [
    15423
  ],
  "31.c.ii" : [
    15493
  ],
  "8.a" : [
    15372
  ],
  "8.c" : [
    15373,
    15375
  ],
  "19|then" : [
    15424
  ],
  "8.e" : [
    15376
  ],
  "8.f" : [
    15385
  ],
  "1" : [
    15348
  ],
  "8.g" : [
    15387
  ],
  "2" : [
    15349
  ],
  "3" : [
    15351
  ],
  "4" : [
    15354
  ],
  "5" : [
    15355
  ],
  "6" : [
    15357
  ],
  "7" : [
    15370
  ],
  "25.e.iv.3.a" : [
    15458
  ],
  "25|else" : [
    15468
  ],
  "9" : [
    15403
  ],
  "25.e.iv" : [
    15451
  ],
  "20" : [
    15425
  ],
  "21" : [
    15427
  ],
  "14.b" : [
    15412
  ],
  "14.a" : [
    15411
  ],
  "25" : [
    15428,
    15468
  ],
  "25.e.ii|if" : [
    15448
  ],
  "25|then" : [
    15429
  ],
  "26" : [
    15469
  ],
  "27" : [
    15470
  ],
  "28" : [
    15473
  ],
  "8.h.i|?1" : [
    15395
  ],
  "6.a.i.1" : [
    15367
  ],
  "31.a.i" : [
    15484
  ],
  "25.e.ii|then" : [
    15449
  ],
  "30" : [
    15474,
    15479
  ],
  "31" : [
    15480,
    15496
  ],
  "25.c.iii|?1" : [
    15442
  ],
  "32" : [
    15497
  ],
  "33" : [
    15498
  ],
  "25.a" : [
    15431
  ],
  "3.a" : [
    15352
  ],
  "7.a" : [
    15371
  ],
  "25.g" : [
    15466
  ],
  "6.a.i" : [
    15363
  ],
  "25.f.ii" : [
    15465
  ],
  "25.f" : [
    15461
  ],
  "25.e" : [
    15445
  ],
  "25.d" : [
    15444
  ],
  "25.c" : [
    15439
  ],
  "25.e.iv.2.a" : [
    15457
  ],
  "6.a.i|else" : [
    15366
  ],
  "25.c.iii" : [
    15441
  ],
  "17|if" : [
    15419
  ],
  "31|then" : [
    15482
  ],
  "8.h.i" : [
    15392
  ],
  "8.e|?2" : [
    15377
  ],
  "6.a|if" : [
    15360,
    15362
  ],
  "25.e.v.1" : [
    15460
  ],
  "31.b.ii" : [
    15488
  ],
  "30|then" : [
    15475
  ],
  "25.e.iv|if" : [
    15452
  ],
  "8.h.ii|then" : [
    15399
  ],
  "31|if" : [
    15481
  ],
  "31.b.i" : [
    15487
  ],
  "25.e.iv|then" : [
    15453
  ],
  "25.a.i" : [
    15433
  ],
  "25.e.i" : [
    15446
  ],
  "6.a" : [
    15369,
    15358
  ],
  "6.a.i|if" : [
    15364
  ],
  "25|if" : [
    15428,
    15430
  ],
  "30|else" : [
    15479
  ],
  "25.e.iv|else" : [
    15454
  ],
  "19|if" : [
    15423
  ],
  "31.c" : [
    15491
  ],
  "17|then" : [
    15420
  ],
  "31.a" : [
    15483
  ],
  "8.g.i" : [
    15389
  ],
  "25.e.iv.2" : [
    15456
  ],
  "25.e.iv.1" : [
    15455
  ],
  "25.e.iv.4" : [
    15459
  ],
  "6.a|else" : [
    15369
  ],
  "10|if" : [
    15405
  ],
  "8.h.ii|if" : [
    15398
  ],
  "10|then" : [
    15406
  ],
  "25.f.i|then" : [
    15464
  ],
  "31.c.i" : [
    15492
  ],
  "25.b.i" : [
    15436
  ],
  "31.c.ii|?1" : [
    15494
  ],
  "25.f.i" : [
    15462
  ],
  "27.a" : [
    15471
  ],
  "8.e|?1" : [
    15382
  ],
  "30|if" : [
    15474,
    15476
  ],
  "6.a|then" : [
    15361
  ]
}