{
  "11|then" : [
    28475
  ],
  "6|?1" : [
    28458
  ],
  "4|?1" : [
    28446
  ],
  "2|?1" : [
    28437
  ],
  "10|?1" : [
    28471
  ],
  "10|else" : [
    28468
  ],
  "19.b" : [
    28491
  ],
  "19.a" : [
    28489
  ],
  "10|if" : [
    28466
  ],
  "12|if" : [
    28476
  ],
  "7|if" : [
    28461
  ],
  "10|then" : [
    28467
  ],
  "10" : [
    28466
  ],
  "11" : [
    28474
  ],
  "5|?1" : [
    28452
  ],
  "4|then" : [
    28443
  ],
  "12" : [
    28476
  ],
  "13" : [
    28478
  ],
  "14" : [
    28479
  ],
  "15" : [
    28481
  ],
  "16" : [
    28486,
    28487
  ],
  "7|then" : [
    28462
  ],
  "19" : [
    28488
  ],
  "1" : [
    28433
  ],
  "2" : [
    28434
  ],
  "3" : [
    28440
  ],
  "11|if" : [
    28474
  ],
  "4" : [
    28442
  ],
  "5" : [
    28449
  ],
  "12|then" : [
    28477
  ],
  "6" : [
    28455
  ],
  "7" : [
    28461
  ],
  "8" : [
    28463
  ],
  "8|then" : [
    28464
  ],
  "9" : [
    28465
  ],
  "15|if" : [
    28482
  ],
  "8|if" : [
    28463
  ],
  "4|if" : [
    28442
  ],
  "15|then" : [
    28483
  ],
  "20" : [
    28493
  ]
}