{
  "2254" : {
    "2254|1" : [
      381675,
      432
    ]
  },
  "2077" : {
    "2077|1" : [
      7908,
      450
    ]
  },
  "2253" : {
    "2253|1" : [
      50358,
      577
    ]
  },
  "2252" : {
    "2252|1" : [
      298255,
      442
    ]
  },
  "2273" : {
    "2271|1-2273|2" : [
      146069,
      434
    ]
  },
  "2052" : {
    "2052|1" : [
      28601,
      513
    ]
  },
  "2272" : {
    "2271|1-2272|2" : [
      468062,
      434
    ]
  },
  "2270" : {
    "2271|1-2270|2" : [
      617368,
      434
    ]
  },
  "minimal" : {
    "minimal" : [
      5886,
      354
    ]
  },
  "2248" : {
    "2248|1" : [
      431795,
      432
    ]
  },
  "2588" : {
    "193|1-2588|1" : [
      73951,
      514
    ]
  },
  "2246" : {
    "2246|1" : [
      141930,
      432
    ]
  },
  "2245" : {
    "2245|1" : [
      227246,
      432
    ]
  },
  "2068" : {
    "2068|1" : [
      54846,
      513
    ]
  },
  "2244" : {
    "2244|1" : [
      559631,
      432
    ]
  },
  "2266" : {
    "2266|1" : [
      22084,
      432
    ]
  },
  "2243" : {
    "2243|1" : [
      181851,
      432
    ]
  },
  "2265" : {
    "2265|1" : [
      496663,
      432
    ]
  },
  "2264" : {
    "2264|1" : [
      68386,
      432
    ]
  },
  "2241" : {
    "2241|1" : [
      740514,
      432
    ]
  },
  "2263" : {
    "2263|1" : [
      44051,
      432
    ]
  },
  "1393" : {
    "1393|1" : [
      1714,
      353
    ]
  },
  "2240" : {
    "2240|1" : [
      733015,
      432
    ]
  },
  "1392" : {
    "1392|1" : [
      1593,
      353
    ]
  },
  "2261" : {
    "2261|2.b.ii" : [
      770873,
      842
    ],
    "2261|1" : [
      111618,
      432
    ]
  },
  "1391" : {
    "1391|1" : [
      1640,
      353
    ]
  },
  "2239" : {
    "2239|1" : [
      47774,
      432
    ]
  },
  "882" : {
    "882|1" : [
      7707,
      273
    ]
  },
  "2259" : {
    "2259|1" : [
      48388,
      432
    ]
  },
  "2258" : {
    "2258|1" : [
      477777,
      432
    ]
  },
  "2059" : {
    "193|1-2059|1" : [
      201087,
      514
    ]
  },
  "2277" : {
    "2277|1" : [
      5886,
      354
    ]
  }
}