{
  "minimal" : {
    "minimal" : [
      1770,
      548
    ]
  },
  "2622" : {
    "2622|2" : [
      7546,
      1456
    ]
  },
  "2620" : {
    "2620|2" : [
      2137,
      1566
    ]
  },
  "2278" : {
    "2796|1-2798|1-2278|1" : [
      1770,
      548
    ],
    "2796|2-2798|1-2278|1" : [
      1770,
      555
    ]
  },
  "2597" : {
    "2597|2" : [
      7738,
      1566
    ]
  },
  "2791" : {
    "2796|1-2800|1-2791|3" : [
      696029,
      2996
    ],
    "2796|2-2800|1-2791|3" : [
      696029,
      3003
    ]
  },
  "2807" : {
    "2812|1-2807|3" : [
      6732,
      1931
    ],
    "2812|3-2807|3" : [
      6732,
      1945
    ],
    "2812|2-2807|3" : [
      6732,
      1938
    ]
  },
  "2790" : {
    "2796|1-2798|1-2790|1" : [
      2084,
      598
    ],
    "2796|2-2798|1-2790|1" : [
      2084,
      605
    ]
  },
  "2806" : {
    "2812|1-2806|3" : [
      7180,
      1839
    ],
    "2812|3-2806|3" : [
      7180,
      1853
    ],
    "2812|2-2806|3" : [
      7180,
      1846
    ]
  },
  "2529" : {
    "2796|1-2798|1-2529|1" : [
      1105,
      593
    ],
    "2796|2-2798|1-2529|1" : [
      1105,
      600
    ]
  },
  "2605" : {
    "2605|2" : [
      5660,
      1456
    ]
  }
}