{
  "1385" : {
    "1385|8" : [
      399,
      412
    ]
  },
  "1440" : {
    "1440|5" : [
      7024,
      799
    ]
  },
  "1384" : {
    "1384|1.d" : [
      6162,
      289
    ]
  },
  "minimal" : {
    "minimal" : [
      264,
      378
    ]
  },
  "1499" : {
    "1505|6.g.ii.3.a-1499|2" : [
      8158,
      1564
    ]
  },
  "1498" : {
    "1505|6.g.ii.3.a-1498|2" : [
      8132,
      1181
    ]
  },
  "1496" : {
    "1505|6.g.ii.3.a-1496|2" : [
      19110,
      22321
    ]
  },
  "899" : {
    "899|6" : [
      6920,
      1135
    ]
  },
  "1419" : {
    "1419|6" : [
      8823,
      1044
    ]
  },
  "1418" : {
    "1418|5.a" : [
      134012,
      926
    ]
  },
  "1417" : {
    "1417|7" : [
      7430,
      946
    ]
  },
  "1416" : {
    "1416|7" : [
      559,
      932
    ]
  },
  "1495" : {
    "1505|6.g.ii.3.a-1495|2" : [
      4587,
      1045
    ]
  },
  "1350" : {
    "1350|5" : [
      7145,
      383
    ]
  },
  "1349" : {
    "1349|5" : [
      2167,
      378
    ]
  },
  "1448" : {
    "1448|5" : [
      470,
      748
    ]
  },
  "1348" : {
    "1348|5" : [
      7177,
      383
    ]
  },
  "1502" : {
    "1505|6.g.ii.3.a-1502|2" : [
      3706,
      4516
    ]
  },
  "1347" : {
    "1347|5" : [
      264,
      378
    ]
  },
  "1501" : {
    "1505|6.g.ii.3.a-1501|2" : [
      1211,
      4973
    ]
  },
  "1445" : {
    "1445|4" : [
      1613,
      702
    ]
  },
  "1388" : {
    "1388|6" : [
      2377,
      375
    ]
  },
  "1387" : {
    "1387|7" : [
      1756,
      378
    ]
  },
  "1420" : {
    "1420|6" : [
      2714,
      1105
    ]
  },
  "1386" : {
    "1386|7" : [
      4823,
      670
    ]
  },
  "900" : {
    "900|6" : [
      7142,
      1150
    ]
  },
  "903" : {
    "903|4.c.i" : [
      7627,
      1185
    ]
  },
  "1407" : {
    "1407|5" : [
      4422,
      819
    ]
  },
  "1406" : {
    "1406|5" : [
      2972,
      804
    ]
  },
  "1449" : {
    "1449|5" : [
      1588,
      763
    ]
  }
}