{
  "minimal" : {
    "minimal" : [
      160417,
      524
    ]
  },
  "1445" : {
    "184|4.b.i-1445|3" : [
      75451,
      1411
    ]
  },
  "2068" : {
    "1085|2-1084|1-2068|4" : [
      189584,
      1371
    ]
  },
  "2750" : {
    "2750|7" : [
      77471,
      1033
    ]
  },
  "2077" : {
    "1085|2-1084|1-2077|4" : [
      245869,
      514
    ]
  },
  "2849" : {
    "1085|2-1084|1-2849|3" : [
      462946,
      558
    ]
  },
  "2061" : {
    "2061|1" : [
      160417,
      524
    ]
  }
}