{
  "1385" : {
    "109|1.a-1389|1.b-1385|7" : [
      321387,
      1557
    ],
    "109|1.a-111|1-1389|4-1385|7" : [
      300120,
      1574
    ]
  },
  "2132" : {
    "109|1.a-112|8-2132|1" : [
      651200,
      1030
    ]
  },
  "2770" : {
    "195|2.a-2770|5" : [
      153788,
      1125
    ]
  },
  "2052" : {
    "195|2.a-2587|1-2052|6" : [
      160167,
      722
    ]
  },
  "1338" : {
    "109|1.a-141|10-1338|6" : [
      217033,
      1384
    ]
  },
  "2603" : {
    "195|2.a-2603|7" : [
      26569,
      615
    ]
  },
  "1359" : {
    "109|1.a-111|1-1389|3-1390|5-1359|2" : [
      43092,
      1279
    ],
    "109|1.a-111|1-1389|4-1390|5-1359|2" : [
      129539,
      1295
    ]
  },
  "1655" : {
    "195|1.b.i-1655|4" : [
      78931,
      2085
    ],
    "195|1.a-1655|4" : [
      68888,
      2689
    ],
    "1655|7.c.ii" : [
      70818,
      7284
    ],
    "195|2.a-1655|4" : [
      432540,
      3266
    ]
  },
  "2744" : {
    "2744|5" : [
      70818,
      7881
    ]
  },
  "minimal" : {
    "minimal" : [
      232964,
      329
    ]
  },
  "1379" : {
    "109|1.a-111|1-1389|4-1390|5-1379|1" : [
      265467,
      793
    ]
  },
  "2105" : {
    "195|2.a-2105|5" : [
      698970,
      591
    ]
  },
  "1356" : {
    "109|1.a-111|1-1356|2" : [
      147758,
      757
    ]
  },
  "1499" : {
    "195|2.a-1504|7.d-1499|1" : [
      30514,
      683
    ],
    "201|3-1505|6.l.ii.4-1499|2" : [
      406337,
      3789
    ],
    "201|3-1505|6.i.iv.2-1499|2" : [
      464923,
      3180
    ]
  },
  "2588" : {
    "195|2.a-193|4-2588|1" : [
      166340,
      763
    ]
  },
  "2621" : {
    "195|2.a-2621|7" : [
      55728,
      615
    ]
  },
  "1256" : {
    "195|2.a-1256|3" : [
      9790,
      381
    ]
  },
  "1355" : {
    "109|1.a-111|1-1355|2" : [
      108190,
      757
    ]
  },
  "1399" : {
    "195|2.a-1399|1" : [
      259742,
      329
    ]
  },
  "1498" : {
    "195|2.a-1504|7.d-1498|1" : [
      28686,
      344
    ],
    "201|3-1505|6.i.iv.2-1498|2" : [
      527468,
      3319
    ]
  },
  "1354" : {
    "109|1.a-112|8-1354|2" : [
      72283,
      764
    ]
  },
  "2586" : {
    "195|2.a-2587|1-2586|7" : [
      9981,
      616
    ]
  },
  "2762" : {
    "195|2.a-2762|5" : [
      204719,
      1125
    ]
  },
  "1297" : {
    "109|1.a-141|10-1297|5" : [
      686528,
      859
    ]
  },
  "1396" : {
    "195|2.a-1396|1" : [
      232964,
      329
    ],
    "201|3-1396|2" : [
      631737,
      1408
    ]
  },
  "2265" : {
    "109|1.a-141|10-2265|5" : [
      718867,
      1426
    ]
  },
  "1296" : {
    "109|1.a-141|10-1296|4" : [
      505795,
      830
    ]
  },
  "1373" : {
    "109|1.a-158|12-158|10-1373|5" : [
      519782,
      798
    ],
    "109|1.a-158|12-1373|5" : [
      545731,
      779
    ]
  },
  "1272" : {
    "109|1.a-142|1-1272|3" : [
      99134,
      1121
    ]
  },
  "1293" : {
    "109|1.a-141|10-1293|4" : [
      118098,
      812
    ]
  },
  "1503" : {
    "195|1.b.i-1504|7.d-1503|1" : [
      90622,
      1588
    ],
    "195|1.a-1504|7.d-1503|1" : [
      58018,
      1533
    ]
  },
  "1403" : {
    "201|3-1403|3.a" : [
      720553,
      3369
    ],
    "201|3-1403|6" : [
      494957,
      4804
    ],
    "195|2.a-1403|1" : [
      145797,
      373
    ]
  },
  "1502" : {
    "195|1.b.i-1504|7.d-1502|1" : [
      150375,
      1587
    ],
    "195|1.a-1504|7.d-1502|1" : [
      177190,
      1532
    ]
  },
  "1303" : {
    "109|1.a-142|1-1306|3-1303|4" : [
      574254,
      1874
    ]
  },
  "1369" : {
    "1372|2-1369|5" : [
      20301,
      599
    ]
  },
  "883" : {
    "201|3-883|3" : [
      326896,
      2950
    ],
    "195|2.a-883|1" : [
      6437,
      341
    ]
  },
  "1401" : {
    "201|3-1401|3.a" : [
      659473,
      3369
    ],
    "201|3-1401|6" : [
      381337,
      3935
    ],
    "195|2.a-1401|1" : [
      426759,
      329
    ]
  },
  "1500" : {
    "201|3-1505|6.i.iv.2-1500|2" : [
      480392,
      2474
    ],
    "195|2.a-1504|7.d-1500|1" : [
      5366,
      368
    ]
  },
  "1400" : {
    "201|3-1400|3" : [
      698702,
      3368
    ],
    "195|2.a-1400|1" : [
      259740,
      329
    ]
  },
  "2478" : {
    "2478|4" : [
      34659,
      592
    ]
  },
  "1366" : {
    "109|1.a-157|2.c-1366|5" : [
      281552,
      820
    ]
  },
  "2059" : {
    "195|2.a-193|4-2059|1" : [
      92118,
      763
    ]
  },
  "2235" : {
    "109|1.a-141|10-2235|2.b" : [
      711336,
      967
    ]
  },
  "1365" : {
    "109|1.a-157|1.b-1365|5" : [
      472933,
      775
    ]
  },
  "2157" : {
    "109|1.a-112|8-2157|1" : [
      141197,
      1030
    ]
  },
  "2773" : {
    "195|2.a-2773|5" : [
      53067,
      1125
    ]
  },
  "2616" : {
    "195|2.a-2587|1-2616|7" : [
      22158,
      616
    ]
  }
}