{
  "1646" : {
    "2798|9-205|2-1133|24-1646|1" : [
      457212,
      2518
    ],
    "2798|9" : [
      343125,
      3161
    ]
  },
  "1623" : {
    "2798|9-205|2-1133|24-1623|1" : [
      245159,
      862
    ]
  },
  "1656" : {
    "2798|9-205|2-1133|24-1656|1" : [
      53384,
      1311
    ]
  },
  "2525" : {
    "2798|9-2528|2-2525|2" : [
      7745,
      623
    ]
  },
  "1611" : {
    "2798|9-205|2-1133|24-1611|1" : [
      7284,
      1014
    ]
  },
  "1754" : {
    "2798|9-205|2-1133|24-1754|2" : [
      63214,
      1743
    ]
  },
  "minimal" : {
    "minimal" : [
      9790,
      578
    ]
  },
  "2277" : {
    "2798|9-2277|4" : [
      9790,
      578
    ]
  }
}