{
  "1435" : {
    "1435|3" : [
      103,
      346
    ]
  },
  "minimal" : {
    "minimal" : [
      34,
      334
    ]
  },
  "1388" : {
    "1388|4" : [
      35267,
      771
    ]
  },
  "1387" : {
    "1387|5" : [
      6706,
      475
    ]
  },
  "1276" : {
    "1276|5" : [
      53403,
      284
    ]
  },
  "1386" : {
    "1386|5" : [
      84793,
      728
    ]
  },
  "1440" : {
    "1440|3" : [
      99,
      646
    ]
  },
  "900" : {
    "900|5.a" : [
      83290,
      1133
    ]
  },
  "1120" : {
    "1120|3" : [
      7490,
      795
    ]
  },
  "1384" : {
    "1384|1.b" : [
      34,
      334
    ]
  },
  "1449" : {
    "1449|4.a" : [
      181094,
      746
    ]
  }
}