{
  "2524" : {
    "168|1-2524|4.c.v.2" : [
      289865,
      898
    ]
  },
  "minimal" : {
    "minimal" : [
      675857,
      1011
    ]
  },
  "2510" : {
    "168|1-2510|6.e.ii" : [
      326353,
      1289
    ],
    "168|1-2510|7" : [
      391559,
      966
    ]
  },
  "2840" : {
    "2840|3" : [
      59865,
      605
    ]
  },
  "2485" : {
    "168|1-2485|18.e.ii" : [
      265943,
      1258
    ]
  },
  "2509" : {
    "168|1-2509|5.i.ii" : [
      294975,
      1503
    ],
    "168|1-2509|5.j.i" : [
      609549,
      1297
    ]
  },
  "2517" : {
    "168|1-2517|16.d.i" : [
      642104,
      2217
    ],
    "168|1-2517|17.b.iv.1" : [
      631361,
      2047
    ]
  },
  "2505" : {
    "168|1-2505|4.e" : [
      675857,
      1011
    ]
  }
}