{
  "minimal" : {
    "minimal" : [
      675857,
      1007
    ]
  },
  "2510" : {
    "1103|1-168|1-2510|6.e.ii" : [
      391176,
      1262
    ],
    "1103|1-168|1-2510|7" : [
      391559,
      962
    ]
  },
  "2485" : {
    "1103|1-168|1-2485|18.e.ii" : [
      57049,
      1584
    ]
  },
  "2509" : {
    "1103|1-168|1-2509|5.i.ii" : [
      294975,
      1499
    ],
    "1103|1-168|1-2509|5.j.i" : [
      609549,
      1293
    ]
  },
  "2517" : {
    "1103|1-168|1-2517|17.b.iv.1" : [
      515877,
      2681
    ],
    "1103|1-168|1-2517|16.d.i" : [
      642104,
      2261
    ]
  },
  "2505" : {
    "1103|1-168|1-2505|4.e" : [
      675857,
      1007
    ]
  }
}