{
  "2045" : {
    "2047|2-2045|3.a" : [
      93364,
      651
    ]
  },
  "2056" : {
    "2057|2-2056|1" : [
      175527,
      566
    ]
  },
  "1274" : {
    "184|3-1274|4" : [
      14539,
      719
    ]
  },
  "2044" : {
    "2044|3.a.ii" : [
      32950,
      590
    ]
  },
  "2055" : {
    "2057|2-2055|1" : [
      21268,
      566
    ]
  },
  "2054" : {
    "2054|2" : [
      25155,
      565
    ]
  },
  "2065" : {
    "182|1-2065|2" : [
      52505,
      566
    ]
  },
  "minimal" : {
    "minimal" : [
      23927,
      434
    ]
  },
  "1445" : {
    "184|3-1445|3" : [
      28895,
      1207
    ]
  },
  "1511" : {
    "1511|5.a.i" : [
      23927,
      434
    ]
  },
  "2049" : {
    "182|1-2049|2" : [
      121969,
      566
    ]
  },
  "2069" : {
    "182|1-2069|2" : [
      34855,
      566
    ]
  },
  "2046" : {
    "2047|2-2046|2" : [
      165230,
      637
    ]
  }
}