{
  "1462" : {
    "1477|3.f.ii-1462|4" : [
      138,
      377
    ]
  },
  "1460" : {
    "1460|2.b" : [
      111,
      347
    ]
  },
  "1338" : {
    "1338|4" : [
      129,
      342
    ]
  },
  "1459" : {
    "1459|2.e" : [
      162,
      359
    ]
  },
  "1453" : {
    "1453|2" : [
      88,
      341
    ]
  },
  "1452" : {
    "1452|2" : [
      160,
      353
    ]
  },
  "1352" : {
    "1352|2" : [
      66,
      338
    ]
  },
  "1472" : {
    "1477|3.a.ii-1472|4" : [
      27037,
      705
    ]
  },
  "1350" : {
    "1350|2" : [
      21,
      338
    ]
  },
  "1471" : {
    "1477|3.a.ii-1471|4" : [
      13230,
      705
    ]
  },
  "1349" : {
    "1349|2" : [
      16,
      338
    ]
  },
  "1348" : {
    "1348|2" : [
      19,
      338
    ]
  },
  "1347" : {
    "1347|2" : [
      22,
      338
    ]
  },
  "1468" : {
    "1477|3.a.ii-1468|4" : [
      15328,
      368
    ],
    "1477|3.f.ii-1468|4" : [
      255039,
      400
    ],
    "1468|1.b" : [
      174,
      346
    ]
  },
  "1467" : {
    "1477|3.a.ii-1467|4" : [
      78628,
      368
    ],
    "1467|1.b" : [
      156,
      346
    ]
  },
  "1500" : {
    "1504|5-1500|1" : [
      13091,
      356
    ]
  },
  "1742" : {
    "1742|8.e" : [
      8992,
      443
    ]
  },
  "1466" : {
    "1466|1.b" : [
      153,
      346
    ],
    "1477|3.f.ii-1466|4" : [
      71231,
      387
    ]
  },
  "1465" : {
    "1465|1.b" : [
      135,
      346
    ]
  },
  "1740" : {
    "1740|8.e" : [
      30691,
      370
    ]
  },
  "1343" : {
    "1343|2" : [
      17,
      338
    ]
  },
  "1464" : {
    "1477|3.a.ii-1464|4" : [
      151,
      358
    ],
    "1477|3.f.ii-1464|4" : [
      76405,
      390
    ]
  },
  "1463" : {
    "1477|3.a.ii-1463|4" : [
      139,
      358
    ]
  },
  "1626" : {
    "1626|2" : [
      246665,
      1197
    ]
  },
  "1363" : {
    "1390|2-1363|1" : [
      58,
      339
    ],
    "1390|4-1363|1" : [
      223860,
      349
    ]
  },
  "1120" : {
    "1120|4.b" : [
      19982,
      906
    ]
  },
  "1362" : {
    "1390|4-1362|1" : [
      136806,
      349
    ],
    "1390|2-1362|1" : [
      54,
      339
    ]
  },
  "1361" : {
    "1390|4-1361|1" : [
      126833,
      349
    ],
    "1390|2-1361|1" : [
      37,
      339
    ]
  },
  "1360" : {
    "1390|4-1360|1" : [
      72703,
      349
    ],
    "1390|2-1360|1" : [
      25,
      339
    ]
  },
  "1359" : {
    "1390|4-1359|2" : [
      234986,
      350
    ],
    "1390|2-1359|2" : [
      29,
      340
    ]
  },
  "1358" : {
    "1390|4-1358|1" : [
      337450,
      349
    ],
    "1390|2-1358|1" : [
      61,
      339
    ]
  },
  "1357" : {
    "1357|2" : [
      14,
      338
    ]
  },
  "1356" : {
    "1356|2" : [
      10,
      338
    ]
  },
  "1355" : {
    "1355|2" : [
      11,
      338
    ]
  },
  "1476" : {
    "1477|3.f.ii-1476|12" : [
      244223,
      542
    ],
    "1477|3.a.ii-1476|12" : [
      18147,
      478
    ]
  },
  "1354" : {
    "1354|2" : [
      15,
      338
    ]
  },
  "1475" : {
    "1477|3.a.ii-1475|12" : [
      17179,
      478
    ]
  },
  "1517" : {
    "1517|2" : [
      190626,
      1048
    ]
  },
  "1757" : {
    "1757|2" : [
      345098,
      3002
    ]
  },
  "1253" : {
    "1253|4" : [
      7941,
      852
    ]
  },
  "1374" : {
    "1374|2" : [
      49,
      338
    ],
    "1374|4" : [
      164861,
      348
    ]
  },
  "1495" : {
    "1504|5-1495|1" : [
      143,
      352
    ]
  },
  "1252" : {
    "1252|4" : [
      22498,
      634
    ]
  },
  "1373" : {
    "1373|2" : [
      47,
      338
    ],
    "1373|4" : [
      66839,
      348
    ]
  },
  "1370" : {
    "1370|2" : [
      46,
      338
    ],
    "1370|4" : [
      82550,
      348
    ]
  },
  "1249" : {
    "1249|3" : [
      82,
      610
    ]
  },
  "1524" : {
    "1525|3-1524|5.a.i" : [
      190470,
      431
    ],
    "1525|3-1524|9.a.i.1" : [
      212406,
      468
    ]
  },
  "1248" : {
    "1248|3" : [
      44,
      392
    ]
  },
  "1369" : {
    "1369|4" : [
      40069,
      348
    ],
    "1369|2" : [
      146,
      338
    ]
  },
  "1523" : {
    "1525|3-1523|5.a.i" : [
      85239,
      425
    ]
  },
  "1368" : {
    "1368|4" : [
      196526,
      348
    ],
    "1368|2" : [
      60,
      338
    ]
  },
  "1522" : {
    "1525|3-1522|9.a.i.1" : [
      272150,
      430
    ]
  },
  "1367" : {
    "1367|2" : [
      45,
      338
    ],
    "1367|4" : [
      65306,
      348
    ]
  },
  "1366" : {
    "1366|2" : [
      24,
      338
    ],
    "1366|4" : [
      27534,
      348
    ]
  },
  "1520" : {
    "1525|3-1520|4.a.i" : [
      479251,
      391
    ]
  },
  "1365" : {
    "1365|2" : [
      43,
      338
    ],
    "1365|4" : [
      224559,
      348
    ]
  },
  "1364" : {
    "1390|2-1364|1" : [
      78,
      339
    ],
    "1390|4-1364|1" : [
      311016,
      349
    ]
  },
  "1526" : {
    "1526|2" : [
      145,
      344
    ]
  },
  "1385" : {
    "1385|4" : [
      10803,
      557
    ],
    "1385|2" : [
      48,
      338
    ]
  },
  "1384" : {
    "1384|4" : [
      223705,
      340
    ],
    "1384|1.c.ii" : [
      34,
      429
    ]
  },
  "1383" : {
    "1383|2" : [
      102,
      338
    ],
    "1383|3.b" : [
      264295,
      351
    ],
    "1383|4.b" : [
      264285,
      351
    ]
  },
  "1382" : {
    "1382|2" : [
      59,
      338
    ],
    "1382|3.b" : [
      171058,
      349
    ]
  },
  "1381" : {
    "1381|6" : [
      64779,
      352
    ],
    "1381|2" : [
      51,
      338
    ]
  },
  "1380" : {
    "1380|6" : [
      28643,
      352
    ],
    "1380|2" : [
      64,
      338
    ]
  },
  "1655" : {
    "1655|3" : [
      480329,
      3286
    ]
  },
  "1379" : {
    "1390|4-1379|1" : [
      214634,
      349
    ],
    "1390|2-1379|1" : [
      28,
      339
    ]
  },
  "1654" : {
    "1654|2" : [
      480815,
      3323
    ]
  },
  "1378" : {
    "1390|4-1378|1" : [
      54266,
      349
    ],
    "1390|2-1378|1" : [
      39,
      339
    ]
  },
  "1499" : {
    "1504|5-1499|1" : [
      19783,
      369
    ]
  },
  "1256" : {
    "1256|2" : [
      93,
      393
    ]
  },
  "1377" : {
    "1390|4-1377|1" : [
      117628,
      349
    ],
    "1390|2-1377|1" : [
      33,
      339
    ]
  },
  "1498" : {
    "1504|5-1498|1" : [
      144,
      352
    ]
  },
  "1376" : {
    "1376|2" : [
      74,
      338
    ],
    "1376|4" : [
      282069,
      348
    ]
  },
  "1497" : {
    "1504|5-1497|1" : [
      92807,
      356
    ]
  },
  "1375" : {
    "1375|2" : [
      71,
      338
    ],
    "1375|4" : [
      380770,
      348
    ]
  },
  "1496" : {
    "1504|5-1496|1" : [
      226,
      369
    ]
  },
  "1275" : {
    "1275|3" : [
      55354,
      356
    ]
  },
  "1274" : {
    "1274|2" : [
      11752,
      752
    ]
  },
  "1272" : {
    "1272|2" : [
      61591,
      354
    ]
  },
  "1303" : {
    "1306|2-1303|4" : [
      462772,
      1462
    ]
  },
  "1301" : {
    "1301|2" : [
      26,
      338
    ]
  },
  "1300" : {
    "1300|2" : [
      75,
      338
    ],
    "1306|2-1300|4" : [
      26274,
      350
    ]
  },
  "1388" : {
    "1388|5.b" : [
      38091,
      862
    ],
    "1388|2" : [
      81,
      338
    ]
  },
  "1421" : {
    "1421|2" : [
      30,
      338
    ],
    "1421|4" : [
      8864,
      348
    ]
  },
  "1387" : {
    "1387|2" : [
      76,
      338
    ],
    "1387|6.b" : [
      14223,
      566
    ]
  },
  "1386" : {
    "1386|2" : [
      68,
      338
    ],
    "1386|6.b" : [
      85010,
      819
    ]
  },
  "1309" : {
    "1310|2-1309|1" : [
      94,
      339
    ]
  },
  "1308" : {
    "1310|2-1308|1" : [
      31,
      339
    ]
  },
  "1549" : {
    "1549|2" : [
      72,
      337
    ]
  },
  "1440" : {
    "1440|4.b" : [
      10290,
      737
    ]
  },
  "1436" : {
    "1436|2" : [
      112,
      351
    ]
  },
  "1435" : {
    "1435|4.b" : [
      9785,
      435
    ]
  },
  "minimal" : {
    "minimal" : [
      3,
      337
    ]
  },
  "1311" : {
    "1311|5" : [
      27,
      341
    ]
  },
  "1276" : {
    "1276|6.b" : [
      54417,
      377
    ]
  },
  "1297" : {
    "1297|4" : [
      253640,
      386
    ]
  },
  "1451" : {
    "1451|2" : [
      3,
      337
    ]
  },
  "1296" : {
    "1296|3" : [
      151865,
      365
    ]
  },
  "1293" : {
    "1293|3" : [
      89,
      339
    ]
  },
  "1291" : {
    "1291|3" : [
      135144,
      4383
    ]
  },
  "1290" : {
    "1290|2" : [
      41779,
      3555
    ]
  },
  "1327" : {
    "1327|2" : [
      57,
      338
    ]
  },
  "1326" : {
    "1326|2" : [
      13895,
      2730
    ]
  },
  "1447" : {
    "1447|2.b" : [
      176601,
      453
    ]
  },
  "1322" : {
    "1322|3" : [
      74384,
      375
    ]
  },
  "1320" : {
    "1320|2" : [
      175215,
      360
    ]
  },
  "1441" : {
    "1441|2" : [
      119,
      351
    ]
  },
  "900" : {
    "900|5.b.ii" : [
      83573,
      1224
    ]
  },
  "902" : {
    "902|3.b" : [
      90508,
      838
    ]
  },
  "1449" : {
    "1449|4.b.ii" : [
      182595,
      837
    ]
  }
}