{
  "10.a.i.1.a|?1" : [
    16633
  ],
  "8.a.iv.2|then" : [
    16616
  ],
  "16|else" : [
    16680
  ],
  "8.a.iv.2|if" : [
    16615
  ],
  "15.b.i" : [
    16653
  ],
  "17.a" : [
    16685
  ],
  "15.b" : [
    16649,
    16665
  ],
  "8.a.iv" : [
    16608
  ],
  "10.a.i" : [
    16624,
    16642
  ],
  "16|if" : [
    16668,
    16670
  ],
  "10" : [
    16643,
    16621
  ],
  "3|if" : [
    16568
  ],
  "11" : [
    16644
  ],
  "4|then" : [
    16593
  ],
  "17|else" : [
    16690
  ],
  "13" : [
    16645,
    16646
  ],
  "15" : [
    16647,
    16666
  ],
  "16" : [
    16680,
    16667
  ],
  "17" : [
    16690,
    16681
  ],
  "18" : [
    16691
  ],
  "4.a" : [
    16594
  ],
  "15.b.i.1" : [
    16655
  ],
  "8.a" : [
    16604
  ],
  "10.a.i.1.c.i" : [
    16641
  ],
  "3.d|if" : [
    16586
  ],
  "10.a.i.1.a" : [
    16630
  ],
  "1" : [
    16564
  ],
  "2" : [
    16566,
    16567
  ],
  "3" : [
    16568,
    16590
  ],
  "4" : [
    16599,
    16591
  ],
  "5" : [
    16600,
    16601
  ],
  "10.a.i.1.b" : [
    16636
  ],
  "17.a|?1" : [
    16688
  ],
  "10.a.i.1.c" : [
    16640
  ],
  "3.d|then" : [
    16587
  ],
  "8" : [
    16602
  ],
  "3.a|then" : [
    16572
  ],
  "9" : [
    16620
  ],
  "15|if" : [
    16647
  ],
  "15.b|if" : [
    16651
  ],
  "10.a.i|else" : [
    16642
  ],
  "10.a" : [
    16623
  ],
  "15.b.ii.1|?1" : [
    16663
  ],
  "17|then" : [
    16683
  ],
  "16.c" : [
    16675
  ],
  "8.a.i" : [
    16605
  ],
  "16.b" : [
    16673
  ],
  "3.a|if" : [
    16571
  ],
  "8.a.iii" : [
    16606
  ],
  "16.a" : [
    16671
  ],
  "10|if" : [
    16621
  ],
  "10.a.i|then" : [
    16627
  ],
  "8.a.iv.1|?1" : [
    16612
  ],
  "16|then" : [
    16669
  ],
  "3|then" : [
    16569
  ],
  "3.c|?1" : [
    16583
  ],
  "10|then" : [
    16622
  ],
  "16.c|?1" : [
    16678
  ],
  "15.b|then" : [
    16652
  ],
  "10.a.i|if" : [
    16626,
    16628
  ],
  "15.b.i.1|?1" : [
    16658
  ],
  "4.a|if" : [
    16595
  ],
  "10.a.i.1" : [
    16629
  ],
  "10.a.i.1.b|then" : [
    16637
  ],
  "3.a" : [
    16570
  ],
  "3.b" : [
    16575
  ],
  "3.c" : [
    16580
  ],
  "3.d" : [
    16586
  ],
  "3.b|then" : [
    16577
  ],
  "3.b|if" : [
    16576
  ],
  "8.a.iv.1" : [
    16609
  ],
  "15.b.ii.1" : [
    16660
  ],
  "8.a.iv.2" : [
    16615
  ],
  "8|then" : [
    16603
  ],
  "4.a|then" : [
    16596
  ],
  "8|if" : [
    16602
  ],
  "10.a.i.1.b|if" : [
    16636
  ],
  "4|if" : [
    16592
  ],
  "15|then" : [
    16648
  ],
  "17|if" : [
    16682,
    16684
  ]
}