{
  "6|?1" : [
    22085
  ],
  "4|?1" : [
    22071
  ],
  "2|?1" : [
    22065
  ],
  "6|then" : [
    22082
  ],
  "9|then" : [
    22095
  ],
  "7|if" : [
    22088
  ],
  "9|if" : [
    22094
  ],
  "5|if" : [
    22074
  ],
  "10" : [
    22096
  ],
  "11" : [
    22101
  ],
  "5|?1" : [
    22078
  ],
  "13" : [
    22103
  ],
  "7|then" : [
    22089
  ],
  "1" : [
    22061
  ],
  "2" : [
    22062
  ],
  "3" : [
    22067
  ],
  "4" : [
    22068
  ],
  "5" : [
    22074
  ],
  "6" : [
    22081
  ],
  "7" : [
    22088
  ],
  "8" : [
    22091
  ],
  "8|then" : [
    22092
  ],
  "9" : [
    22094
  ],
  "6|if" : [
    22081
  ],
  "8|if" : [
    22091
  ],
  "5|then" : [
    22075
  ]
}